scilab_kernel/__init__.py
scilab_kernel/__main__.py
scilab_kernel/_make_figures.sci
scilab_kernel/_version.py
scilab_kernel/check.py
scilab_kernel/kernel.json
scilab_kernel/kernel.py
scilab_kernel/images/logo-32x32.png
scilab_kernel/images/logo-64x64.png
scilab_kernel/magics/plot_magic.py
scilab_kernel-0.10.2.dist-info/METADATA
scilab_kernel-0.10.2.dist-info/WHEEL
scilab_kernel-0.10.2.dist-info/licenses/LICENSE.txt
scilab_kernel-0.10.2.dist-info/RECORD
