Metadata-Version: 2.4
Name: scilab-kernel
Version: 0.10.2
Summary: 'A Jupyter kernel for Scilab.'
Project-URL: Homepage, http://github.com/Calysto/scilab_kernel
Author-email: 'Steven Silvester' <steven.silvester@ieee.org>, 'Douglas Blank' <doug.blank@gmail.com>
Maintainer-email: Vincent Couvert <vincent.couvert@3ds.com>
License: Copyright (c) 2014-2025 Scilab Kernel Developers
License-File: LICENSE.txt
Classifier: Intended Audience :: Science/Research
Classifier: License :: OSI Approved :: BSD License
Classifier: Operating System :: OS Independent
Classifier: Programming Language :: Python
Classifier: Programming Language :: Python :: 3
Classifier: Topic :: Scientific/Engineering
Classifier: Topic :: Software Development
Classifier: Topic :: System :: Shells
Requires-Python: >=3.7
Requires-Dist: ipykernel
Requires-Dist: jupyter-client>=4.3.0
Requires-Dist: metakernel>=0.24.0
Provides-Extra: test
Requires-Dist: jupyter-kernel-test; extra == 'test'
Requires-Dist: nbconvert; extra == 'test'
Requires-Dist: pytest; extra == 'test'
